README.rst
setup.py
src/easy_menu/__init__.py
src/easy_menu/easy_menu.py
src/easy_menu/exceptions.py
src/easy_menu.egg-info/PKG-INFO
src/easy_menu.egg-info/SOURCES.txt
src/easy_menu.egg-info/dependency_links.txt
src/easy_menu.egg-info/entry_points.txt
src/easy_menu.egg-info/pbr.json
src/easy_menu.egg-info/requires.txt
src/easy_menu.egg-info/top_level.txt
src/easy_menu/controller/__init__.py
src/easy_menu/controller/command_executor.py
src/easy_menu/controller/executor.py
src/easy_menu/entity/__init__.py
src/easy_menu/entity/command.py
src/easy_menu/entity/command_line.py
src/easy_menu/entity/item.py
src/easy_menu/entity/menu.py
src/easy_menu/entity/meta.py
src/easy_menu/logger/__init__.py
src/easy_menu/logger/logger.py
src/easy_menu/logger/system_logger.py
src/easy_menu/setting/__init__.py
src/easy_menu/setting/arg_parser.py
src/easy_menu/setting/loader.py
src/easy_menu/setting/setting.py
src/easy_menu/view/__init__.py
src/easy_menu/view/terminal.py
src/easy_menu/view/i18n/__init__.py
src/easy_menu/view/i18n/messages_en.py
src/easy_menu/view/i18n/messages_ja.py