Metadata-Version: 1.0
Name: easy-menu
Version: 1.3.1
Summary: Super Simple Terminal Command Launcher Generator
Home-page: https://github.com/mogproject/easy-menu
Author: mogproject
Author-email: mogproj@gmail.com
License: Apache 2.0 License
Platform: UNKNOWN
